code_challenge_helper/__init__.py
code_challenge_helper/__main__.py
code_challenge_helper/cli.py
code_challenge_helper/generator.py
code_challenge_helper/templates/Excalidraw.md
code_challenge_helper/templates/go/Solution.go
code_challenge_helper/templates/go/Tests.go
code_challenge_helper/templates/java/Solution.java
code_challenge_helper/templates/java/Tests.java
code_challenge_helper/templates/python/Solution.py
code_challenge_helper/templates/python/Tests.py
code_challenge_helper-0.1.1.dist-info/licenses/LICENCE
code_challenge_helper-0.1.1.dist-info/METADATA
code_challenge_helper-0.1.1.dist-info/WHEEL
code_challenge_helper-0.1.1.dist-info/entry_points.txt
code_challenge_helper-0.1.1.dist-info/top_level.txt
code_challenge_helper-0.1.1.dist-info/RECORD
