Metadata-Version: 2.4
Name: code-challenge-helper
Version: 0.1.1
Summary: Ferramenta para criar estrutura de pastas para estudos de desafios de código
Author-email: Roberto Luis de Jesus Santos Junior <contato.robertoluis@gmail.com>
Project-URL: GitHub Repository, https://github.com/RobertsLuis/code_challenges_helper
Keywords: python,cli,challenge,helper,code,challenge-helper
Classifier: Programming Language :: Python :: 3
Classifier: License :: OSI Approved :: MIT License
Classifier: Operating System :: OS Independent
Requires-Python: >=3.7
License-File: LICENCE
Requires-Dist: click>=8.0.0
Requires-Dist: jinja2>=3.0.0
Requires-Dist: InquirerPy>=0.3.4
Dynamic: license-file
